irate/__init__.py
tests/__init__.py
irate-0.0.1.dist-info/LICENSE
irate-0.0.1.dist-info/METADATA
irate-0.0.1.dist-info/WHEEL
irate-0.0.1.dist-info/top_level.txt
irate-0.0.1.dist-info/RECORD
