Metadata-Version: 2.1
Name: irate
Version: 0.0.1
Summary: A library for doing static analysis in/on Python
Home-page: https://github.com/operator-9/irate
Author: Jon Riehl
Author-email: jon.riehl@gmail.com
License: UNKNOWN
Platform: UNKNOWN
Classifier: Programming Language :: Python :: 3
Classifier: License :: OSI Approved :: MIT License
Classifier: Operating System :: OS Independent
Requires-Python: >=3.6
